[{"ID":27083,"Name":"Ashton","Lat":-44.0333,"Lon":171.7667,"CountryCode":null},{"ID":568,"Name":"Auckland","Lat":-36.8406,"Lon":174.74,"CountryCode":null},{"ID":19559,"Name":"Blenheim","Lat":-41.514,"Lon":173.96,"CountryCode":null},{"ID":26040,"Name":"Cambridge","Lat":-37.8833,"Lon":175.4667,"CountryCode":null},{"ID":1865,"Name":"Christchurch","Lat":-43.531,"Lon":172.6365,"CountryCode":null},{"ID":6163,"Name":"Dunedin","Lat":-45.8742,"Lon":170.5036,"CountryCode":null},{"ID":26991,"Name":"Feilding","Lat":-40.2167,"Lon":175.5667,"CountryCode":null},{"ID":15572,"Name":"Gisborne","Lat":-38.6625,"Lon":178.0178,"CountryCode":null},{"ID":42225,"Name":"Glencoe","Lat":-46.1833,"Lon":168.6833,"CountryCode":null},{"ID":46388,"Name":"Greymouth","Lat":-42.45,"Lon":171.2075,"CountryCode":null},{"ID":47441,"Name":"Halfmoon Bay","Lat":-46.9,"Lon":168.1333,"CountryCode":null},{"ID":3659,"Name":"Hamilton","Lat":-37.7833,"Lon":175.2833,"CountryCode":null},{"ID":32410,"Name":"Havelock North","Lat":-39.6667,"Lon":176.8833,"CountryCode":null},{"ID":42103,"Name":"Hawera","Lat":-39.5933,"Lon":174.2783,"CountryCode":null},{"ID":46941,"Name":"Hokitika","Lat":-42.7156,"Lon":170.9681,"CountryCode":null},{"ID":11735,"Name":"Invercargill","Lat":-46.4131,"Lon":168.3475,"CountryCode":null},{"ID":47041,"Name":"Kaikoura","Lat":-42.4,"Lon":173.68,"CountryCode":null},{"ID":47472,"Name":"Kairaki","Lat":-43.386,"Lon":172.703,"CountryCode":null},{"ID":46588,"Name":"Kaitaia","Lat":-35.1125,"Lon":173.2628,"CountryCode":null},{"ID":46474,"Name":"Kerikeri","Lat":-35.2244,"Lon":173.9514,"CountryCode":null},{"ID":27109,"Name":"Levin","Lat":-40.6219,"Lon":175.2867,"CountryCode":null},{"ID":5959,"Name":"Lower Hutt","Lat":-41.2167,"Lon":174.9167,"CountryCode":null},{"ID":28469,"Name":"Macetown","Lat":-44.8667,"Lon":168.8333,"CountryCode":null},{"ID":1886,"Name":"Manukau City","Lat":-37,"Lon":174.885,"CountryCode":null},{"ID":24870,"Name":"Masterton","Lat":-40.97,"Lon":175.65,"CountryCode":null},{"ID":33331,"Name":"Mosgiel","Lat":-45.875,"Lon":170.3486,"CountryCode":null},{"ID":9298,"Name":"Napier","Lat":-39.4903,"Lon":176.9178,"CountryCode":null},{"ID":11986,"Name":"Nelson","Lat":-41.2708,"Lon":173.2839,"CountryCode":null},{"ID":9955,"Name":"New Plymouth","Lat":-39.0578,"Lon":174.0742,"CountryCode":null},{"ID":3216,"Name":"Northcote","Lat":-36.8019,"Lon":174.7494,"CountryCode":null},{"ID":7762,"Name":"Palmerston North","Lat":-40.355,"Lon":175.6117,"CountryCode":null},{"ID":18261,"Name":"Paraparaumu","Lat":-40.9144,"Lon":175.0056,"CountryCode":null},{"ID":44285,"Name":"Paraparaumu Beach","Lat":-40.8938,"Lon":174.9794,"CountryCode":null},{"ID":10343,"Name":"Porirua","Lat":-41.1333,"Lon":174.85,"CountryCode":null},{"ID":47069,"Name":"Pukekohe East","Lat":-37.2,"Lon":174.9,"CountryCode":null},{"ID":30675,"Name":"Richmond","Lat":-41.3333,"Lon":173.1833,"CountryCode":null},{"ID":28777,"Name":"Rolleston","Lat":-43.5833,"Lon":172.3833,"CountryCode":null},{"ID":10506,"Name":"Rotorua","Lat":-38.1378,"Lon":176.2514,"CountryCode":null},{"ID":46599,"Name":"Stratford","Lat":-39.3333,"Lon":174.2833,"CountryCode":null},{"ID":21548,"Name":"Taupo","Lat":-38.6875,"Lon":176.0694,"CountryCode":null},{"ID":4209,"Name":"Tauranga","Lat":-37.6833,"Lon":176.1667,"CountryCode":null},{"ID":47029,"Name":"Te Anau","Lat":-45.4167,"Lon":167.7167,"CountryCode":null},{"ID":35713,"Name":"Te Awamutu","Lat":-38.0167,"Lon":175.3167,"CountryCode":null},{"ID":46444,"Name":"Thames","Lat":-37.1383,"Lon":175.5375,"CountryCode":null},{"ID":18920,"Name":"Timaru","Lat":-44.3931,"Lon":171.2508,"CountryCode":null},{"ID":33064,"Name":"Tokoroa","Lat":-38.2167,"Lon":175.8667,"CountryCode":null},{"ID":46872,"Name":"Turangi","Lat":-38.9889,"Lon":175.8083,"CountryCode":null},{"ID":13351,"Name":"Upper Hutt","Lat":-41.1333,"Lon":175.05,"CountryCode":null},{"ID":35885,"Name":"Waikanae","Lat":-40.875,"Lon":175.0639,"CountryCode":null},{"ID":47070,"Name":"Waitakere","Lat":-36.85,"Lon":174.543,"CountryCode":null},{"ID":47071,"Name":"Waitangi","Lat":-43.9514,"Lon":-176.5611,"CountryCode":null},{"ID":43994,"Name":"Waiuku","Lat":-37.249,"Lon":174.73,"CountryCode":null},{"ID":44950,"Name":"Wanaka","Lat":-44.7,"Lon":169.15,"CountryCode":null},{"ID":3077,"Name":"Wellington","Lat":-41.2889,"Lon":174.7772,"CountryCode":null},{"ID":46722,"Name":"Westport","Lat":-41.7581,"Lon":171.6022,"CountryCode":null},{"ID":29568,"Name":"Whakatane","Lat":-37.96,"Lon":176.98,"CountryCode":null},{"ID":13855,"Name":"Whanganui","Lat":-39.9325,"Lon":175.0519,"CountryCode":null},{"ID":11107,"Name":"Whangarei","Lat":-35.725,"Lon":174.3236,"CountryCode":null}]